LICENSE
MANIFEST.in
README.rst
requirements.txt
setup.py
version.py
alignak_notifications/__init__.py
alignak_notifications.egg-info/PKG-INFO
alignak_notifications.egg-info/SOURCES.txt
alignak_notifications.egg-info/dependency_links.txt
alignak_notifications.egg-info/not-zip-safe
alignak_notifications.egg-info/top_level.txt
alignak_notifications/etc/arbiter/packs/notifications/commands.cfg
alignak_notifications/etc/arbiter/packs/notifications/notification-ways.cfg
alignak_notifications/etc/arbiter/packs/resource.d/notifications.cfg
alignak_notifications/json/notifications/commands.json
alignak_notifications/json/notifications/setup.sh
alignak_notifications/libexec/alignak.png
alignak_notifications/libexec/alignak_blue.png
alignak_notifications/libexec/notify_by_email.py
alignak_notifications/libexec/notify_by_slack.py